MANIFEST.in
README.txt
setup.py
metnav/HISTORY.txt
metnav/INSTALL.txt
metnav/README.txt
metnav/VERSION.txt
metnav/__init__.py
metnav/config.py
metnav/configure.zcml
metnav/functions.py
metnav/overrides.zcml
metnav/profiles.zcml
metnav/setuphandlers.py
metnav/tests.py
metnav/tool.gif
metnav/tool.py
metnav.egg-info/PKG-INFO
metnav.egg-info/SOURCES.txt
metnav.egg-info/dependency_links.txt
metnav.egg-info/entry_points.txt
metnav.egg-info/namespace_packages.txt
metnav.egg-info/not-zip-safe
metnav.egg-info/paster_plugins.txt
metnav.egg-info/requires.txt
metnav.egg-info/top_level.txt
metnav/browser/XML.py
metnav/browser/__init__.py
metnav/browser/configure.zcml
metnav/browser/header.py
metnav/browser/res_archives.py
metnav/browser/res_dossiers.py
metnav/browser/res_dossierthematique.py
metnav/browser/res_news.py
metnav/browser/res_published.py
metnav/browser/res_semaine.py
metnav/browser/search.py
metnav/browser/search_adv_md.py
metnav/browser/themes.py
metnav/browser/themes_v0.py
metnav/browser/visitscount.py
metnav/browser/templates/XMLPDF.pt
metnav/browser/templates/res_archives.pt
metnav/browser/templates/res_dossiers.pt
metnav/browser/templates/res_news.pt
metnav/browser/templates/res_search.pt
metnav/browser/templates/res_semaine.pt
metnav/browser/templates/search.pt
metnav/browser/templates/themes.pt
metnav/docs/ensskinner_config.patch
metnav/docs/metnav.lyx
metnav/docs/patch_ensskinner.txt
metnav/i18n/metnav-en.po
metnav/i18n/metnav-fr.po
metnav/i18n/metnav-fr.po.autosave
metnav/i18n/metnav-tmp.pot
metnav/i18n/metnav.pot
metnav/i18n/rebuild_pot.sh
metnav/i18n/report.txt
metnav/interfaces/__init__.py
metnav/portlets/__init__.py
metnav/portlets/classification.py
metnav/portlets/classification_v0.py
metnav/portlets/configure.zcml
metnav/portlets/events2.py
metnav/portlets/hasard.py
metnav/portlets/mostView.py
metnav/portlets/news2.py
metnav/portlets/objects.py
metnav/portlets/objectsMedias.py
metnav/portlets/objectsPeda.py
metnav/portlets/recent2.py
metnav/portlets/related.py
metnav/portlets/related_dossier.py
metnav/portlets/search2.py
metnav/portlets/semaine.py
metnav/portlets/serie.py
metnav/portlets/topnews.py
metnav/portlets/templates/classification.pt
metnav/portlets/templates/events.pt
metnav/portlets/templates/events2.pt
