Metadata-Version: 1.1
Name: metnav
Version: 4.0.1
Summary: Facet Metadata Navigation from eXist and LOM-fr
Home-page: http://unis.ens-lyon.fr
Author: UNIS (ENS Lyon)
Author-email: unis@ens-lyon.fr
License: CeCILL-B
Keywords: Plone eXist-db facet navigation LOM LOM-fr
Platform: UNKNOWN
Classifier: Framework :: Plone
Classifier: Programming Language :: Python
